shreqt/__init__.py
shreqt/connection.py
shreqt/core.py
shreqt/layer.py
shreqt/layer_query.py
shreqt/model.py
shreqt/sqlalchemy_ext.py
shreqt-0.6.2.dist-info/WHEEL
shreqt-0.6.2.dist-info/METADATA
shreqt-0.6.2.dist-info/RECORD
