Metadata-Version: 2.1
Name: shreqt
Version: 0.6.2
Summary: Query Testing framework
Keywords: testing,query,exasol
Author: Zibi Rzepka
Author-email: zibi.rzepka@revolut.com
Requires-Python: >=3.6,<4.0
Classifier: Programming Language :: Python :: 3
Classifier: Programming Language :: Python :: 3.6
Classifier: Programming Language :: Python :: 3.7
Classifier: Programming Language :: Python :: 3.8
Requires-Dist: pyexasol (==0.9.1)
Requires-Dist: sqlalchemy (>=1.3,<2.0)
Requires-Dist: sqlalchemy-exasol (>=2.0,<3.0)
Requires-Dist: sqlparse (>=0.3.0,<0.4.0)
